{
  "BOT_LOGIN": "Er is een bot kanaal account aangemaakt.",
  "BOT_MUTE": "Bot gedempt.",
  "BOT_UNMUTE": "Bot niet langer gedempt.",
  "BOT_JOIN": "De bot heeft het kanaal betreden.",
  "BOT_LEAVE": "De bot heeft het kanaal verlaten.",
  "BOT_MOD": "De bot is als moderator gedetecteerd.",
  "BOT_UNMOD": "De bot is niet als moderator gedetecteerd.",

  "RECEIVE_DONATION": "$[0] Aan Fossabot gedoneerd. Bedankt!",

  "COMMAND_CREATE": "Het commando is aangemaakt met als reactie: {0}.",
  "COMMAND_EDIT_RESPONSE": "De reactie van het commando is aangepast van {0} naar {1}.",
  "COMMAND_EDIT_GLOBAL_COOLDOWN": "De globale wachttijd van het commando is aangepast van [0] secs naar [1] secs.",
  "COMMAND_EDIT_USER_COOLDOWN": "De gebruikers wachttijd van het commando is aangepast van [0] secs naar [1] secs.",
  "COMMAND_EDIT_MODE": "Commando modus veranderd van {0} nar {1}.",
  "COMMAND_EDIT_NAME": "Comando naam van <code class=\"fossabot-code\">![0]</code> naar <code class=\"fossabot-code\">![1]</code> veranderd.",
  "COMMAND_EDIT_MINUSERLEVEL": "minimum gebruikers niveau veranderd van {0} naar {1}.",
  "COMMAND_DISABLE": "Commando uitgeschakeld.",
  "COMMAND_ENABLE": "Commando ingeschakeld.",
  "COMMAND_DELETE": "Commando verwijderd.",

  "TIMER_CREATE": "De timer is aangemaakt.",
  "TIMER_ENABLE": "De timer is ingeschakeld.",
  "TIMER_DISABLE": "De timer is uitgeschakeld.",
  "TIMER_ADD_COMMAND": "Commando <code class=\"fossabot-code\">![0]</code> aan de timer toegevoegd.",
  "TIMER_REMOVE_COMMAND": "Commando <code class=\"fossabot-code\">![0]</code> van de timer verwijderd.",
  "TIMER_DELETE": "De timer is verwijderd.",
  "TIMER_CHANGE_NAME": "Naam van de timer veranderd van {0} naar {1}.",
  "TIMER_CHANGE_INTERVAL": "Interval van de timer veranderd van {0} mins nar {1} mins.",
  "TIMER_CHANGE_MINLINES": "Minimum aantal chat regels aangepast van {0} naar {1}.",

  "FILTER_ENABLE": "Filter ingeschakeld.",
  "FILTER_DISABLE": "Filter uitgeschakeld.",
  "FILTER_TIMEOUT_LENGTH": "Timeout lengte veranderd van {0} secs naar {1} secs.",
  "FILTER_TIMEOUT_REASON": "Tiemout reden veranderd van {0} naar {1}.",
  "FILTER_ANNOUNCE_ENABLE": "Filter toegestaan om in de chat aan te kondigen.",
  "FILTER_ANNOUNCE_DISABLE": "Filter niet toegestaan om aan te kondigen in de chat.",
  "FILTER_WARNING_ENABLE": "Sta toe dat gebruikers waarschuwingen van het filter ontvangen.",
  "FILTER_WARNING_DISABLE": "Gebruikers niet toegestaan waarschuwingen van het filter te ontvangen.",
  "FILTER_WARNING_TIMEOUT": "Waarschuwings timeout lengte veranderd van [0]s naar [1]s.",
  "FILTER_MINCHARS": "Minimum aantal tekens in het chat begricht veranderd van [0] naar [0].",
  "FILTER_LINKS_PERMIT_ENABLE": "Gebruikers toestaan om gerpermit te worden voor het filter.",
  "FILTER_LINKS_PERMIT_DISABLE": "Gebruikers niet toestaan om gerpermit te worden voor het filter.",
  "FILTER_LINKS_PERMIT_TIME": "Permit lengte van het filter veranderd van [0] secs naar [1] secs.",
  "FILTER_LINKS_WHITELIST_ADD": "Link {0} toegestaan.",
  "FILTER_LINKS_WHITELIST_REMOVE": "Link {0} niet langer toegestaan.",
  "FILTER_CAPS_MODE": "De filtermoderatiemodus veranderd van {0} naar {1}.",
  "FILTER_CAPS_MAX_PERCENT": "Maximaal caps percentage per bericht veranderd van {0} naar {1}.",
  "FILTER_CAPS_MAX_VALUE": "Maximaal aantal hoofdletters per bericht veranderd van {0} naar {1}.",
  "FILTER_EMOTES_MAX": "Maximaal aantal emoticons per bericht veranderd van {0} naar {1}.",
  "FILTER_LENGTH_MAX": "Maximale bericht lengte veranderd van {0} naar {1} .",
  "FILTER_REPETITION_MAX": "Maximale aantal toegestaande herhalingen veranderd van {0} naar {1}.",
  "FILTER_SYMBOL_MAX": "Maximaal aantal toegestane symbolen veranderd van {0} naar {1}.",

  "BAN_CREATE": "{0} toegevoegd aan de banlijst. (Reden: {1})",
  "BAN_REMOVE": "{0} verwijderd van de banlijst.",
  "BAN_REASON_CHANGE": "Ban reden van {0} veranderd van {1} naar {2}.",
  "BAN_USERNAME_CHANGE": "Verbannen gebruikers naam veranderd van {0} naar {1}.",

  "EDITOR_CREATE_EDITOR": "Gebruiker {0} toegevoegd als kanaal editor.",
  "EDITOR_REMOVE_EDITOR": "Gebruiker {0} verwijderd als kanaal editor.",
  "EDITOR_CREATE_ADMIN": "Gebruiker {0} toegevoegd als kanaal admin.",
  "EDITOR_REMOVE_ADMIN": "Gebruiker {0} verwijderd als kanaal admin.",

  "ALERTS_ENABLE": "{0} chat notificatie ingeschakeld.",
  "ALERTS_DISABLE": "{1} chat notificatie uitgeschakeld.",
  "ALERTS_MESSAGE_CHANGE": "{0} chat notificatie veranderd van {1} naar {1}.",
  "ALERTS_MESSAGE_SET": "[0] Chat notificatie ingesteld als {2}.",

  "TWITTER_ENABLE": "Live tweets ingeschakeld.",
  "TWITTER_DISABLE": "Live tweets uitgeschakeld.",
  "TWITTER_TEMPLATE": "Sjabloon veranderd van {0} naar {1}.",
  "TWITTER_REMOVE": "Gebruiker {0} verwijderd van de live feed.",
  "TWITTER_ADD": "Gebruiker {1} toegevoegd aan de live feed.",

  "CHANNEL_CHANGE_INFO": "Kanaal [0] veranderd van {1} naar {2}.",
  "CHANNEL_AUTHORIZE": "Gebruiker verleende Fossabot extra autorisaties aan het kanaal.",
  "CHANNEL_UNAUTHORIZE": "Extra autorisaties van het kanaal verwijderd. (Reden: {0})",
  "CHANNEL_PERMIT_USER": "Permitted {0} for [1] secs.",

  "STREAMLABS_AUTH": "Geautoriseerd met Streamlabs.",
  "STREAMLABS_REAUTH": "Opnieuw Geautoriseerd met Streamlabs.",
  "STREAMLABS_UNAUTH": "Niet meer Geautoriseerd met Streamlabs. (Reden: {0})",
  "STREAMLABS_ENABLE": "Alerts ingeschakeld.",
  "STREAMLABS_DISABLE": "Alerts uitgeschakeld.",
  "STREAMLABS_CHANGE_TEMPLATE": "Sjabloon veranderd van {0} naar {1}.",
  "STREAMLABS_CHANGE_INTERVAL": "Interval veranderd van {0} secs naar {1} secs.",
  "STREAMLABS_CHANGE_MINAMNT": "Minimale donatie bedrag veranderd van {0} naar {1}.",

  "DISCORD_NOTIF_ENABLE": "Notificaties ingeschakeld.",
  "DISCORD_NOTIF_DISABLE": "Notificaties uitgeschakeld.",
  "DISCORD_NOTIF_WEBHOOK_UPDATE": "Webhook URL geupdate van {0} naar {1}.",
  "DISCORD_NOTIF_TEMPLATE_UPDATE": "Sjabloon veranderd van {0} naar {1}."
}
